gradle.properties
hexdoc_lessertp/__gradle_version__.py
hexdoc_lessertp/__init__.py
hexdoc_lessertp/__version__.py
hexdoc_lessertp/_hooks.py
hexdoc_lessertp/py.typed
hexdoc_lessertp/_export/.gitignore
hexdoc_lessertp/_export/__init__.py
hexdoc_lessertp/_export/generated/__init__.py
hexdoc_lessertp/_export/generated/lessertp.hexdoc.json
hexdoc_lessertp/_export/generated/lessertp.patterns.hexdoc.json
hexdoc_lessertp/_export/generated/assets/hexcasting/patchouli_books/thehexbook/en_us/entries/lesserteleport.json
hexdoc_lessertp/_export/generated/assets/hexcasting/patchouli_books/thehexbook/en_us/entries/simplerteleport.json
hexdoc_lessertp/_export/generated/assets/lessertp/lang/en_us.flatten.json5
hexdoc_lessertp/_export/generated/assets/lessertp/lang/en_us.json
hexdoc_lessertp/_export/generated/assets/lessertp/lang/zh_cn.flatten.json5
hexdoc_lessertp/_export/generated/assets/lessertp/lang/zh_cn.json
hexdoc_lessertp/_templates/__init__.py
hexdoc_lessertp-1.2.1.1.2.dev0.dist-info/METADATA
hexdoc_lessertp-1.2.1.1.2.dev0.dist-info/WHEEL
hexdoc_lessertp-1.2.1.1.2.dev0.dist-info/entry_points.txt
hexdoc_lessertp-1.2.1.1.2.dev0.dist-info/licenses/LICENSE
hexdoc_lessertp-1.2.1.1.2.dev0.dist-info/RECORD
