Metadata-Version: 2.4
Name: hexdoc-lessertp
Version: 1.2.1.1.2.dev0
Summary: Python web book docgen and hexdoc plugin for Lesser Teleport.
Project-URL: Homepage, https://real-luxof.github.io/Lesser-Teleport/
Project-URL: Source, https://github.com/Real-Luxof/Lesser-Teleport
Author: Real-Luxof
License-File: LICENSE
Keywords: hexdoc
Requires-Python: >=3.11
Requires-Dist: hexdoc-hexcasting~=0.11.2.1.0
Provides-Extra: dev
Requires-Dist: ruff~=0.11.2; extra == 'dev'
